tria_hr_data_gatherer/__init__.py
tria_hr_data_gatherer/exceptions.py
tria_hr_data_gatherer/gatherer.py
tria_hr_data_gatherer-0.1.1.dist-info/METADATA
tria_hr_data_gatherer-0.1.1.dist-info/WHEEL
tria_hr_data_gatherer-0.1.1.dist-info/top_level.txt
tria_hr_data_gatherer-0.1.1.dist-info/RECORD
